{
 "venue_id": "thecvf.com/CVPR/2024/Workshop/SynData4CV",
 "source_api": "v2",
 "fetched_at": "2026-06-10T23:46:15.106Z",
 "paper_count": 43,
 "papers": [
  {
   "title": "A Benchmark Synthetic Dataset for C-SLAM in Service Environments",
   "authors": [
    "Harin Park",
    "Inha Lee",
    "Minje Kim",
    "Hyungyu Park",
    "Kyungdon Joo"
   ],
   "forum_url": "https://openreview.net/forum?id=p6igw3ldIc",
   "pdf_url": "https://openreview.net/pdf?id=p6igw3ldIc"
  },
  {
   "title": "A Neural Model for High-Performance Scanning Electron Microscopy Image Simulation of Porous Materials",
   "authors": [
    "Tim Dahmen",
    "Markus Kronenberger",
    "Niklas Rottmayer",
    "Katja Schladitz",
    "Claudia Redenbach"
   ],
   "forum_url": "https://openreview.net/forum?id=SwO84a6yA5",
   "pdf_url": "https://openreview.net/pdf?id=SwO84a6yA5"
  },
  {
   "title": "An Approach to Synthesize Thermal Infrared Ship Images",
   "authors": [
    "Doan Thinh Vo",
    "Phan Anh Đức",
    "Nguyen Nhu Thao",
    "Huong Ninh"
   ],
   "forum_url": "https://openreview.net/forum?id=XQQ12dIR7C",
   "pdf_url": "https://openreview.net/pdf?id=XQQ12dIR7C"
  },
  {
   "title": "Attributed Synthetic Data Generation for Zero-shot Image Classification",
   "authors": [
    "Shijian Wang",
    "Linxin Song",
    "Ryotaro Shimizu",
    "Masayuki Goto",
    "Hanqian wu"
   ],
   "forum_url": "https://openreview.net/forum?id=k4Xnh0EPus",
   "pdf_url": "https://openreview.net/pdf?id=k4Xnh0EPus"
  },
  {
   "title": "Balancing Quality and Quantity: The Impact of Synthetic Data on Smoke Detection Accuracy in Computer Vision",
   "authors": [
    "Ethan Seefried",
    "Changsoo Jung",
    "Jack Fitzgerald",
    "Mariah Bradford",
    "Trevor Chartier",
    "Nathaniel Blanchard"
   ],
   "forum_url": "https://openreview.net/forum?id=ckhhCcGq9n",
   "pdf_url": "https://openreview.net/pdf?id=ckhhCcGq9n"
  },
  {
   "title": "Beyond Internet Images: Evaluating Vision-Language Models for Domain Generalization on Synthetic-to-Real Industrial Datasets",
   "authors": [
    "Louis Hémadou",
    "Héléna Vorobieva",
    "Ewa Kijak",
    "Frederic Jurie"
   ],
   "forum_url": "https://openreview.net/forum?id=BgpApqspGw",
   "pdf_url": "https://openreview.net/pdf?id=BgpApqspGw"
  },
  {
   "title": "CinePile: A Long Video Question Answering Dataset and Benchmark",
   "authors": [
    "Ruchit Rawal",
    "Khalid Saifullah",
    "Ronen Basri",
    "David Jacobs",
    "Gowthami Somepalli",
    "Tom Goldstein"
   ],
   "forum_url": "https://openreview.net/forum?id=3Bv2Sz54lV",
   "pdf_url": "https://openreview.net/pdf?id=3Bv2Sz54lV"
  },
  {
   "title": "CompoDiff: Versatile Composed Image Retrieval With Latent Diffusion",
   "authors": [
    "Geonmo Gu",
    "Sanghyuk Chun",
    "Wonjae Kim",
    "HeeJae Jun",
    "Yoohoon Kang",
    "Sangdoo Yun"
   ],
   "forum_url": "https://openreview.net/forum?id=gYE6LBojgM",
   "pdf_url": "https://openreview.net/pdf?id=gYE6LBojgM"
  },
  {
   "title": "Compositional Learning of Visually-Grounded Concepts Using Reinforcement",
   "authors": [
    "Zijun Lin",
    "Haidi Azaman",
    "M Ganesh Kumar",
    "Cheston Tan"
   ],
   "forum_url": "https://openreview.net/forum?id=XusBKwfVxX",
   "pdf_url": "https://openreview.net/pdf?id=XusBKwfVxX"
  },
  {
   "title": "DDOS: The Drone Depth and Obstacle Segmentation Dataset",
   "authors": [
    "Benedikt Kolbeinsson",
    "Krystian Mikolajczyk"
   ],
   "forum_url": "https://openreview.net/forum?id=FZxofmVOwg",
   "pdf_url": "https://openreview.net/pdf?id=FZxofmVOwg"
  },
  {
   "title": "DGInStyle: Domain-Generalizable Semantic Segmentation with Image Diffusion Models and Stylized Semantic Control",
   "authors": [
    "Yuru Jia",
    "Lukas Hoyer",
    "Shengyu Huang",
    "Tianfu Wang",
    "Luc Van Gool",
    "Konrad Schindler",
    "Anton Obukhov"
   ],
   "forum_url": "https://openreview.net/forum?id=WgRrHFlyLU",
   "pdf_url": "https://openreview.net/pdf?id=WgRrHFlyLU"
  },
  {
   "title": "DiffInject: Revisiting Debias via Synthetic Data Generation using Diffusion-based Style Injection",
   "authors": [
    "Donggeun Ko",
    "Sangwoo Jo",
    "Dongjun Lee",
    "Namjun Park",
    "Jaekwang KIM"
   ],
   "forum_url": "https://openreview.net/forum?id=jSB5wlUU3p",
   "pdf_url": "https://openreview.net/pdf?id=jSB5wlUU3p"
  },
  {
   "title": "DISC: Latent Diffusion Models with Self-Distillation from Separated Conditions for Prostate Cancer Grading",
   "authors": [
    "Man M. Ho",
    "Elham Ghelichkhan",
    "Yosep Chong",
    "Yufei Zhou",
    "Beatrice S. Knudsen",
    "Tolga Tasdizen"
   ],
   "forum_url": "https://openreview.net/forum?id=NcCAy6PXNF",
   "pdf_url": "https://openreview.net/pdf?id=NcCAy6PXNF"
  },
  {
   "title": "DreamSync: Aligning Text-to-Image Generation with Image Understanding Feedback",
   "authors": [
    "Jiao Sun",
    "Deqing Fu",
    "Yushi Hu",
    "Su Wang",
    "Royi Rassin",
    "Da-Cheng Juan",
    "Dana Alon",
    "Charles Herrmann",
    "Sjoerd van Steenkiste",
    "Ranjay Krishna",
    "Cyrus Rashtchian"
   ],
   "forum_url": "https://openreview.net/forum?id=cAFgDFprbC",
   "pdf_url": "https://openreview.net/pdf?id=cAFgDFprbC"
  },
  {
   "title": "From NeRF to 3DGS: A Leap in Stereo Dataset Quality?",
   "authors": [
    "Magnus Kaufmann Gjerde",
    "Filip Slezák",
    "Joakim Bruslund Haurum",
    "Thomas B. Moeslund"
   ],
   "forum_url": "https://openreview.net/forum?id=cesQERAXhi",
   "pdf_url": "https://openreview.net/pdf?id=cesQERAXhi"
  },
  {
   "title": "Gen2Det: Generate to Detect",
   "authors": [
    "Saksham Suri",
    "Fanyi Xiao",
    "Animesh Sinha",
    "Sean Culatana",
    "Raghuraman Krishnamoorthi",
    "Chenchen Zhu",
    "Abhinav Shrivastava"
   ],
   "forum_url": "https://openreview.net/forum?id=g5PfpoSoat",
   "pdf_url": "https://openreview.net/pdf?id=g5PfpoSoat"
  },
  {
   "title": "GenAI-Bench: A Holistic Benchmark for Compositional Text-to-Visual Generation",
   "authors": [
    "Baiqi Li",
    "Zhiqiu Lin",
    "Deepak Pathak",
    "Jiayao Emily Li",
    "Xide Xia",
    "Graham Neubig",
    "Pengchuan Zhang",
    "Deva Ramanan"
   ],
   "forum_url": "https://openreview.net/forum?id=hJm7qnW3ym",
   "pdf_url": "https://openreview.net/pdf?id=hJm7qnW3ym"
  },
  {
   "title": "GeomVerse: A Systematic Evaluation of Large Models for Geometric Reasoning",
   "authors": [
    "Mehran Kazemi",
    "Hamidreza Alvari",
    "Ankit Anand",
    "Jialin Wu",
    "Xi Chen",
    "Radu Soricut"
   ],
   "forum_url": "https://openreview.net/forum?id=A9NOAS0hn1",
   "pdf_url": "https://openreview.net/pdf?id=A9NOAS0hn1"
  },
  {
   "title": "Harlequin: Color-driven Generation of Synthetic Data for Referring Expression Comprehension",
   "authors": [
    "Luca Parolari",
    "Elena Izzo",
    "Lamberto Ballan"
   ],
   "forum_url": "https://openreview.net/forum?id=EZYvU2oC6J",
   "pdf_url": "https://openreview.net/pdf?id=EZYvU2oC6J"
  },
  {
   "title": "HDL-SAM: A Hybrid Deep Learning Framework for High-Resolution Imaging in Scanning Acoustic Microscopy",
   "authors": [
    "Akshit Sharma",
    "Ayush Somani",
    "Pragyan Banerjee",
    "Frank Melandsø",
    "Anowarul Habib"
   ],
   "forum_url": "https://openreview.net/forum?id=WlBqPK2uLa",
   "pdf_url": "https://openreview.net/pdf?id=WlBqPK2uLa"
  },
  {
   "title": "Implicit Neural Clustering",
   "authors": [
    "Thomas Kreutz",
    "Max Mühlhäuser",
    "Alejandro Sanchez Guinea"
   ],
   "forum_url": "https://openreview.net/forum?id=VSFR5eBP7h",
   "pdf_url": "https://openreview.net/pdf?id=VSFR5eBP7h"
  },
  {
   "title": "Inclusive Portrait Lighting Estimation Model Leveraging Graphic-Based Synthetic Data",
   "authors": [
    "Kin Ching Lydia Chau",
    "Tao LI",
    "Ruowei Jiang",
    "Zhi Yu",
    "Panagiotis-Alexandros Bokaris"
   ],
   "forum_url": "https://openreview.net/forum?id=J0p8qKsWl0",
   "pdf_url": "https://openreview.net/pdf?id=J0p8qKsWl0"
  },
  {
   "title": "Intrinsic LoRA: A Generalist Approach for Discovering Knowledge in Generative Models",
   "authors": [
    "Xiaodan Du",
    "Nicholas Kolkin",
    "Greg Shakhnarovich",
    "Anand Bhattad"
   ],
   "forum_url": "https://openreview.net/forum?id=xHKWN3Yi6U",
   "pdf_url": "https://openreview.net/pdf?id=xHKWN3Yi6U"
  },
  {
   "title": "LAESI: Leaf Area Estimation with Synthetic Imagery",
   "authors": [
    "Jacek Kałużny",
    "Yannik Schreckenberg",
    "Karol Cyganik",
    "Peter Annighöfer",
    "Soren Pirk",
    "Dominik Michels",
    "Mikolaj Cieslak",
    "Farhah Assaad",
    "Bedrich Benes",
    "Wojtek Palubicki"
   ],
   "forum_url": "https://openreview.net/forum?id=Skh18goLXF",
   "pdf_url": "https://openreview.net/pdf?id=Skh18goLXF"
  },
  {
   "title": "m&m's: A Benchmark to Evaluate Tool-Use for multi-step multi-modal Tasks",
   "authors": [
    "Zixian Ma",
    "Weikai Huang",
    "Jieyu Zhang",
    "Tanmay Gupta",
    "Ranjay Krishna"
   ],
   "forum_url": "https://openreview.net/forum?id=ZV9XDgmTvf",
   "pdf_url": "https://openreview.net/pdf?id=ZV9XDgmTvf"
  },
  {
   "title": "MICDrop: Masking Image and Depth Features via Complementary Dropout for Domain-Adaptive Semantic Segmentation",
   "authors": [
    "Linyan Yang",
    "Lukas Hoyer",
    "Mark Weber",
    "Tobias Fischer",
    "Dengxin Dai",
    "Laura Leal-Taixé",
    "Daniel Cremers",
    "Marc Pollefeys",
    "Luc Van Gool"
   ],
   "forum_url": "https://openreview.net/forum?id=25vcM0vPyD",
   "pdf_url": "https://openreview.net/pdf?id=25vcM0vPyD"
  },
  {
   "title": "Object-Conditioned Energy-Based Model for Attention Map Alignment in Text-to-Image Diffusion Models",
   "authors": [
    "Yasi Zhang",
    "Peiyu Yu",
    "Ying Nian Wu"
   ],
   "forum_url": "https://openreview.net/forum?id=XFYqhBBB61",
   "pdf_url": "https://openreview.net/pdf?id=XFYqhBBB61"
  },
  {
   "title": "On the Equivalency, Substitutability, and Flexibility of Synthetic Data",
   "authors": [
    "Che-Jui Chang",
    "Danrui Li",
    "Seonghyeon Moon",
    "Mubbasir Kapadia"
   ],
   "forum_url": "https://openreview.net/forum?id=8cd6gOPm7o",
   "pdf_url": "https://openreview.net/pdf?id=8cd6gOPm7o"
  },
  {
   "title": "Paved2Paradise: Cost-Effective and Scalable LiDAR Simulation by Factoring the Real World",
   "authors": [
    "Michael A. Alcorn",
    "Noah Schwartz"
   ],
   "forum_url": "https://openreview.net/forum?id=D9sfy3NUbY",
   "pdf_url": "https://openreview.net/pdf?id=D9sfy3NUbY"
  },
  {
   "title": "R3DS: Reality-linked 3D Scenes for Panoramic Scene Understanding",
   "authors": [
    "Qirui Wu",
    "Sonia Raychaudhuri",
    "Daniel Ritchie",
    "Manolis Savva",
    "Angel X Chang"
   ],
   "forum_url": "https://openreview.net/forum?id=B7PKwbqNdo",
   "pdf_url": "https://openreview.net/pdf?id=B7PKwbqNdo"
  },
  {
   "title": "S2MGen: A Synthetic Skin Mask Generator for Improving Segmentation",
   "authors": [
    "Subhadra Gopalakrishnan",
    "Trisha Mittal",
    "Jaclyn Pytlarz",
    "Yuheng Zhao"
   ],
   "forum_url": "https://openreview.net/forum?id=i5tZ9szbTt",
   "pdf_url": "https://openreview.net/pdf?id=i5tZ9szbTt"
  },
  {
   "title": "Self-Distillation on Conditional Spatial Activation Maps for ForeGround-BackGround Segmentation",
   "authors": [
    "Yeruru Asrar Ahmed",
    "Anurag Mittal"
   ],
   "forum_url": "https://openreview.net/forum?id=48zldWWWNi",
   "pdf_url": "https://openreview.net/pdf?id=48zldWWWNi"
  },
  {
   "title": "SEVD: Synthetic Event-based Vision Dataset for Ego and Fixed Traffic Perception",
   "authors": [
    "Manideep Reddy Aliminati",
    "Bharatesh Chakravarthi",
    "Aayush Atul Verma",
    "Arpitsinh Vaghela",
    "Hua Wei",
    "Xuesong Zhou",
    "Yezhou Yang"
   ],
   "forum_url": "https://openreview.net/forum?id=I1vrc56Vau",
   "pdf_url": "https://openreview.net/pdf?id=I1vrc56Vau"
  },
  {
   "title": "SIFTer: Self-improving Synthetic Datasets for Pre-training Classification Models",
   "authors": [
    "Ryo Hayamizu",
    "Shota Nakamura",
    "Sora Takashima",
    "Hirokatsu Kataoka",
    "Ikuro Sato",
    "Nakamasa Inoue",
    "Rio Yokota"
   ],
   "forum_url": "https://openreview.net/forum?id=EvDZlcHNDo",
   "pdf_url": "https://openreview.net/pdf?id=EvDZlcHNDo"
  },
  {
   "title": "SynthCLIP: Are We Ready for a Fully Synthetic CLIP Training?",
   "authors": [
    "Hasan Abed Al Kader Hammoud",
    "Hani Itani",
    "Fabio Pizzati",
    "Adel Bibi",
    "Bernard Ghanem"
   ],
   "forum_url": "https://openreview.net/forum?id=oKwYycMSrf",
   "pdf_url": "https://openreview.net/pdf?id=oKwYycMSrf"
  },
  {
   "title": "Training Robust Classifiers with Diffusion Denoised Examples",
   "authors": [
    "Chandramouli Shama Sastry",
    "Sri Harsha Dumpala",
    "Sageev Oore"
   ],
   "forum_url": "https://openreview.net/forum?id=T1eCXQuWE2",
   "pdf_url": "https://openreview.net/pdf?id=T1eCXQuWE2"
  },
  {
   "title": "Training with Real instead of Synthetic Generated Images Still Performs Better",
   "authors": [
    "Scott Geng",
    "Ranjay Krishna",
    "Pang Wei Koh"
   ],
   "forum_url": "https://openreview.net/forum?id=7YnS0mYl8s",
   "pdf_url": "https://openreview.net/pdf?id=7YnS0mYl8s"
  },
  {
   "title": "Uncertainty Inclusive Contrastive Learning for Leveraging Synthetic Images",
   "authors": [
    "Fiona Cai",
    "Emily Mu",
    "John Guttag"
   ],
   "forum_url": "https://openreview.net/forum?id=wNKOQVcMDS",
   "pdf_url": "https://openreview.net/pdf?id=wNKOQVcMDS"
  },
  {
   "title": "UrbanIR: Large-Scale Urban Scene Inverse Rendering from a Single Video",
   "authors": [
    "Zhi-Hao Lin",
    "Bohan Liu",
    "Yi-Ting Chen",
    "David Forsyth",
    "Jia-Bin Huang",
    "Anand Bhattad",
    "Shenlong Wang"
   ],
   "forum_url": "https://openreview.net/forum?id=0sMJfHCyk2",
   "pdf_url": "https://openreview.net/pdf?id=0sMJfHCyk2"
  },
  {
   "title": "Video2Game: Real-time, Interactive, Realistic and Browser-Compatible Environment from a Single Video",
   "authors": [
    "Hongchi Xia",
    "Zhi-Hao Lin",
    "Wei-Chiu Ma",
    "Shenlong Wang"
   ],
   "forum_url": "https://openreview.net/forum?id=4xURVbKlCt",
   "pdf_url": "https://openreview.net/pdf?id=4xURVbKlCt"
  },
  {
   "title": "Virtually Enriched NYU Depth V2 Dataset for Monocular Depth Estimation: Do We Need Artificial Augmentation?",
   "authors": [
    "Dmitry Yu. Ignatov",
    "Andrey Ignatov",
    "Radu Timofte"
   ],
   "forum_url": "https://openreview.net/forum?id=X2cmDAjprN",
   "pdf_url": "https://openreview.net/pdf?id=X2cmDAjprN"
  },
  {
   "title": "Visual Program Distillation: Distilling Tools and Programmatic Reasoning into Vision-Language Models",
   "authors": [
    "Yushi Hu",
    "Otilia Stretcu",
    "Chun-Ta Lu",
    "Krishnamurthy Viswanathan",
    "Kenji Hata",
    "Enming Luo",
    "Ranjay Krishna",
    "Ariel Fuxman"
   ],
   "forum_url": "https://openreview.net/forum?id=Uq6uBK6n5d",
   "pdf_url": "https://openreview.net/pdf?id=Uq6uBK6n5d"
  },
  {
   "title": "XIMAGENET-12: An Explainable Visual Benchmark Dataset for Model Robustness Evaluation",
   "authors": [
    "Qiang Li",
    "Dan Zhang",
    "Shengzhao Lei",
    "Xun Zhao",
    "WeiWei Li",
    "Porawit Kamnoedboon",
    "Junhao Dong",
    "Shuyan Li"
   ],
   "forum_url": "https://openreview.net/forum?id=4tbbxtGwou",
   "pdf_url": "https://openreview.net/pdf?id=4tbbxtGwou"
  }
 ]
}
